MANIFEST.in
setup.py
page_block/__init__.py
page_block/admin.py
page_block/apps.py
page_block/models.py
page_block/tests.py
page_block.egg-info/PKG-INFO
page_block.egg-info/SOURCES.txt
page_block.egg-info/dependency_links.txt
page_block.egg-info/requires.txt
page_block.egg-info/top_level.txt
page_block/migrations/0001_initial.py
page_block/migrations/0002_auto_20170916_1708.py
page_block/migrations/0003_auto_20171004_1248.py
page_block/migrations/0004_auto_20171007_1749.py
page_block/migrations/0005_auto_20171025_1641.py
page_block/migrations/0006_pageblockurl.py
page_block/migrations/0007_auto_20190623_1726.py
page_block/migrations/__init__.py
page_block/templates/page_block/card.html
page_block/templates/page_block/lead.html
page_block/templatetags/__init__.py
page_block/templatetags/page_block.py