Metadata-Version: 1.0
Name: page-block
Version: 1.0.6
Summary: Simple CMS-like app that allows you to dump admin editable blocks of markdown into pages via template tag.
Home-page: UNKNOWN
Author: Jacek Bzdak
Author-email: jacek@askesis.pl
License: MIT
Platform: UNKNOWN
